{
  "filename": "doc.pdf.11_0.pdf",
  "pages": [
    {
      "i": 0,
      "blocks": [
        {
          "i": 0,
          "bbox": [
            233,
            31,
            1416,
            69
          ],
          "type": "abandon",
          "lines": [
            {
              "i": 0,
              "bbox": [
                238.500001695421,
                36.54593891567654,
                1414.2667134602864,
                69.87927224900987
              ],
              "content": "Case: 1:16-cv-10634 Document #: 11 Filed: 07/20/18 Page 1 of 1 PageID #:168"
            }
          ]
        },
        {
          "i": 1,
          "bbox": [
            349,
            106,
            1405,
            223
          ],
          "type": "title",
          "lines": [
            {
              "i": 0,
              "bbox": [
                566.2083519829644,
                101.99506547715929,
                1186.5715874565972,
                152.7783923678928
              ],
              "content": "UNITED STATES DISTRICT COURT"
            },
            {
              "i": 1,
              "bbox": [
                353.13890245225696,
                138.6617660522461,
                1399.6420118543836,
                189.44509294297958
              ],
              "content": "FOR THE Northern District of Illinois \u2212 CM/ECF LIVE, Ver 6.2.2"
            },
            {
              "i": 2,
              "bbox": [
                746.5166727701823,
                175.3284666273329,
                1006.2632242838541,
                226.1117935180664
              ],
              "content": "Eastern Division"
            }
          ]
        },
        {
          "i": 2,
          "bbox": [
            206,
            289,
            604,
            331
          ],
          "type": "text",
          "lines": [
            {
              "i": 0,
              "bbox": [
                207.21668667263455,
                282.49562581380206,
                601.3466729058159,
                331.408945719401
              ],
              "content": "Jo Anne Singletary Rogers"
            }
          ]
        },
        {
          "i": 3,
          "bbox": [
            702,
            332,
            835,
            373
          ],
          "type": "text",
          "lines": [
            {
              "i": 0,
              "bbox": [
                704.3861389160156,
                326.3761732313368,
                833.7461683485243,
                375.28949313693573
              ],
              "content": "Plaintiff,"
            }
          ]
        },
        {
          "i": 4,
          "bbox": [
            957,
            377,
            1454,
            463
          ],
          "type": "text",
          "lines": [
            {
              "i": 0,
              "bbox": [
                960.9749688042534,
                370.2567206488715,
                1347.5883483886719,
                419.17004055447046
              ],
              "content": "Case No.: 1:16\u2212cv\u221210634"
            },
            {
              "i": 1,
              "bbox": [
                960.9749688042534,
                414.13726806640625,
                1449.741956922743,
                463.0505879720052
              ],
              "content": "Honorable Rebecca R. Pallmeyer"
            }
          ]
        },
        {
          "i": 5,
          "bbox": [
            206,
            386,
            235,
            414
          ],
          "type": "text",
          "lines": [
            {
              "i": 0,
              "bbox": [
                207.21668667263455,
                370.2567206488715,
                234.71669091118704,
                419.17004055447046
              ],
              "content": "v."
            }
          ]
        },
        {
          "i": 6,
          "bbox": [
            205,
            465,
            491,
            505
          ],
          "type": "text",
          "lines": [
            {
              "i": 0,
              "bbox": [
                207.21664428710938,
                458.017815483941,
                489.29337395562067,
                506.9311353895399
              ],
              "content": "Zimmer, Inc., et al."
            }
          ]
        },
        {
          "i": 7,
          "bbox": [
            702,
            509,
            868,
            549
          ],
          "type": "text",
          "lines": [
            {
              "i": 0,
              "bbox": [
                704.3860965304905,
                501.89836290147565,
                866.2694295247395,
                550.8116828070746
              ],
              "content": "Defendant."
            }
          ]
        },
        {
          "i": 8,
          "bbox": [
            550,
            655,
            1200,
            700
          ],
          "type": "title",
          "lines": [
            {
              "i": 0,
              "bbox": [
                555.0249735514323,
                651.8033345540364,
                1197.7550082736545,
                702.5866614447699
              ],
              "content": "NOTIFICATION OF DOCKET ENTRY"
            }
          ]
        },
        {
          "i": 9,
          "bbox": [
            208,
            810,
            1189,
            853
          ],
          "type": "text",
          "lines": [
            {
              "i": 0,
              "bbox": [
                207.21664428710938,
                805.3538852267795,
                1186.9500901963975,
                854.2672051323784
              ],
              "content": "This docket entry was made by the Clerk on Friday, July 20, 2018:"
            }
          ]
        },
        {
          "i": 10,
          "bbox": [
            206,
            921,
            1507,
            1035
          ],
          "type": "text",
          "lines": [
            {
              "i": 0,
              "bbox": [
                207.21664428710938,
                915.3539021809895,
                1384.4000074598523,
                964.2672220865885
              ],
              "content": "            MINUTE entry before the Honorable Rebecca R. Pallmeyer: Pursuant to"
            },
            {
              "i": 1,
              "bbox": [
                207.21664428710938,
                952.0206027560763,
                1507.709757486979,
                1000.9339226616753
              ],
              "content": "Stipulation, the above cause is dismissed with prejudice. The parties shall bear their own"
            },
            {
              "i": 2,
              "bbox": [
                207.21664428710938,
                988.6873033311632,
                1334.4597710503472,
                1037.6006232367622
              ],
              "content": "costs and attorney fees. MDL member case terminated. Mailed notice. (etv, )"
            }
          ]
        },
        {
          "i": 11,
          "bbox": [
            206,
            1192,
            1501,
            1378
          ],
          "type": "text",
          "lines": [
            {
              "i": 0,
              "bbox": [
                207.21664428710938,
                1186.451212565104,
                1490.476820203993,
                1237.5645107693142
              ],
              "content": "ATTENTION: This notice is being sent pursuant to Rule 77(d) of the Federal Rules of"
            },
            {
              "i": 1,
              "bbox": [
                207.21664428710938,
                1223.117913140191,
                1392.5765143500435,
                1272.0312330457898
              ],
              "content": "Civil Procedure or Rule 49(c) of the Federal Rules of Criminal Procedure. It was"
            },
            {
              "i": 2,
              "bbox": [
                207.21664428710938,
                1259.7846137152778,
                1471.116468641493,
                1308.6979336208767
              ],
              "content": "generated by CM/ECF, the automated docketing system used to maintain the civil and"
            },
            {
              "i": 3,
              "bbox": [
                207.21664428710938,
                1296.4513142903645,
                1496.4533487955728,
                1345.3646341959634
              ],
              "content": "criminal dockets of this District. If a minute order or other document is enclosed, please"
            },
            {
              "i": 4,
              "bbox": [
                207.21664428710938,
                1333.1180148654514,
                742.8800794813368,
                1382.0313347710503
              ],
              "content": "refer to it for additional information."
            }
          ]
        },
        {
          "i": 12,
          "bbox": [
            205,
            1412,
            1495,
            1491
          ],
          "type": "text",
          "lines": [
            {
              "i": 0,
              "bbox": [
                207.21664428710938,
                1406.4512464735242,
                1490.4032389322915,
                1455.3646511501736
              ],
              "content": "For scheduled events, motion practices, recent opinions and other information, visit our"
            },
            {
              "i": 1,
              "bbox": [
                207.21664428710938,
                1443.117947048611,
                723.6667209201389,
                1493.607923719618
              ],
              "content": "web site at www.ilnd.uscourts.gov."
            }
          ]
        }
      ]
    }
  ]
}