{
  "filename": "doc.pdf.187_0.pdf",
  "pages": [
    {
      "i": 0,
      "blocks": [
        {
          "i": 0,
          "bbox": [
            317,
            38,
            1383,
            76
          ],
          "type": "abandon",
          "lines": [
            {
              "i": 0,
              "bbox": [
                323.0,
                44.0,
                1379.0,
                73.0
              ],
              "content": "Case 2:17-cv-00894-TSZ  Document 187 Filed 06/05/20  Page 1 of 2"
            }
          ]
        },
        {
          "i": 1,
          "bbox": [
            129,
            190,
            183,
            2181
          ],
          "type": "abandon",
          "lines": [
            {
              "i": 0,
              "bbox": [
                152.0,
                209.0,
                171.0,
                236.0
              ],
              "content": "1"
            },
            {
              "i": 1,
              "bbox": [
                148.0,
                286.0,
                176.0,
                323.0
              ],
              "content": "2"
            },
            {
              "i": 2,
              "bbox": [
                148.0,
                454.0,
                176.0,
                490.0
              ],
              "content": "4"
            },
            {
              "i": 3,
              "bbox": [
                149.0,
                530.0,
                172.0,
                575.0
              ],
              "content": "5"
            },
            {
              "i": 4,
              "bbox": [
                146.0,
                619.0,
                176.0,
                655.0
              ],
              "content": "6"
            },
            {
              "i": 5,
              "bbox": [
                148.0,
                701.0,
                176.0,
                738.0
              ],
              "content": "7"
            },
            {
              "i": 6,
              "bbox": [
                146.0,
                784.0,
                176.0,
                823.0
              ],
              "content": "8"
            },
            {
              "i": 7,
              "bbox": [
                146.0,
                866.0,
                176.0,
                903.0
              ],
              "content": "9"
            },
            {
              "i": 8,
              "bbox": [
                132.0,
                951.0,
                178.0,
                988.0
              ],
              "content": "10"
            },
            {
              "i": 9,
              "bbox": [
                134.0,
                1036.0,
                171.0,
                1068.0
              ],
              "content": "11"
            },
            {
              "i": 10,
              "bbox": [
                132.0,
                1114.0,
                176.0,
                1155.0
              ],
              "content": "12"
            },
            {
              "i": 11,
              "bbox": [
                132.0,
                1199.0,
                176.0,
                1238.0
              ],
              "content": "13"
            },
            {
              "i": 12,
              "bbox": [
                134.0,
                1286.0,
                176.0,
                1315.0
              ],
              "content": "14"
            },
            {
              "i": 13,
              "bbox": [
                136.0,
                1366.0,
                171.0,
                1400.0
              ],
              "content": "15"
            },
            {
              "i": 14,
              "bbox": [
                136.0,
                1451.0,
                176.0,
                1483.0
              ],
              "content": "16"
            },
            {
              "i": 15,
              "bbox": [
                136.0,
                1533.0,
                171.0,
                1565.0
              ],
              "content": "17"
            },
            {
              "i": 16,
              "bbox": [
                136.0,
                1618.0,
                173.0,
                1648.0
              ],
              "content": "18"
            },
            {
              "i": 17,
              "bbox": [
                136.0,
                1700.0,
                171.0,
                1730.0
              ],
              "content": "19"
            },
            {
              "i": 18,
              "bbox": [
                134.0,
                1783.0,
                173.0,
                1813.0
              ],
              "content": "20"
            },
            {
              "i": 19,
              "bbox": [
                132.0,
                1865.0,
                171.0,
                1898.0
              ],
              "content": "21"
            },
            {
              "i": 20,
              "bbox": [
                134.0,
                1950.0,
                173.0,
                1982.0
              ],
              "content": "22"
            },
            {
              "i": 21,
              "bbox": [
                129.0,
                2028.0,
                173.0,
                2067.0
              ],
              "content": "23"
            }
          ]
        },
        {
          "i": 2,
          "bbox": [
            520,
            534,
            1178,
            658
          ],
          "type": "title",
          "lines": [
            {
              "i": 0,
              "bbox": [
                561.0,
                539.0,
                1139.0,
                571.0
              ],
              "content": "UNITED STATES DISTRICT COURT"
            },
            {
              "i": 1,
              "bbox": [
                524.0,
                582.0,
                1176.0,
                612.0
              ],
              "content": "WESTERN DISTRICT OF WASHINGTON"
            },
            {
              "i": 2,
              "bbox": [
                744.0,
                623.0,
                959.0,
                655.0
              ],
              "content": "AT SEATTLE"
            }
          ]
        },
        {
          "i": 3,
          "bbox": [
            227,
            719,
            558,
            761
          ],
          "type": "text",
          "lines": [
            {
              "i": 0,
              "bbox": [
                231.0,
                724.0,
                552.0,
                756.0
              ],
              "content": "EKO BRANDS, LLC,"
            }
          ]
        },
        {
          "i": 4,
          "bbox": [
            547,
            797,
            679,
            838
          ],
          "type": "text",
          "lines": [
            {
              "i": 0,
              "bbox": [
                545.0,
                798.0,
                681.0,
                836.0
              ],
              "content": "Plaintiff,"
            }
          ]
        },
        {
          "i": 5,
          "bbox": [
            293,
            888,
            324,
            918
          ],
          "type": "text",
          "lines": [
            {
              "i": 0,
              "bbox": [
                293.0,
                889.0,
                326.0,
                919.0
              ],
              "content": "V."
            }
          ]
        },
        {
          "i": 6,
          "bbox": [
            917,
            888,
            1126,
            929
          ],
          "type": "text",
          "lines": [
            {
              "i": 0,
              "bbox": [
                919.0,
                891.0,
                1123.0,
                924.0
              ],
              "content": "C17-894 TSZ"
            }
          ]
        },
        {
          "i": 7,
          "bbox": [
            225,
            962,
            683,
            1088
          ],
          "type": "text",
          "lines": [
            {
              "i": 0,
              "bbox": [
                231.0,
                967.0,
                677.0,
                997.0
              ],
              "content": "ADRIAN RIVERA MAYNEZ"
            },
            {
              "i": 1,
              "bbox": [
                231.0,
                1011.0,
                626.0,
                1043.0
              ],
              "content": "ENTERPRISES, INC.; and"
            },
            {
              "i": 2,
              "bbox": [
                231.0,
                1052.0,
                520.0,
                1084.0
              ],
              "content": "ADRIAN RIVERA,"
            }
          ]
        },
        {
          "i": 8,
          "bbox": [
            917,
            971,
            1195,
            1012
          ],
          "type": "text",
          "lines": [
            {
              "i": 0,
              "bbox": [
                922.0,
                976.0,
                1194.0,
                1008.0
              ],
              "content": "MINUTE ORDER"
            }
          ]
        },
        {
          "i": 9,
          "bbox": [
            547,
            1125,
            724,
            1164
          ],
          "type": "text",
          "lines": [
            {
              "i": 0,
              "bbox": [
                544.0,
                1123.0,
                722.0,
                1165.0
              ],
              "content": "Defendants."
            }
          ]
        },
        {
          "i": 10,
          "bbox": [
            191,
            1225,
            1432,
            1311
          ],
          "type": "text",
          "lines": [
            {
              "i": 0,
              "bbox": [
                300.0,
                1231.0,
                1421.0,
                1263.0
              ],
              "content": "The following Minute Order is made by direction of the Court, the Honorable"
            },
            {
              "i": 1,
              "bbox": [
                196.0,
                1274.0,
                864.0,
                1306.0
              ],
              "content": "Thomas S. Zilly, United States District Judge:."
            }
          ]
        },
        {
          "i": 11,
          "bbox": [
            194,
            1341,
            1494,
            1969
          ],
          "type": "text",
          "lines": [
            {
              "i": 0,
              "bbox": [
                296.0,
                1348.0,
                349.0,
                1382.0
              ],
              "content": "(1)"
            },
            {
              "i": 1,
              "bbox": [
                395.0,
                1347.0,
                1462.0,
                1380.0
              ],
              "content": "Defendants' motion to alter or amend judgment or alternatively for a new."
            },
            {
              "i": 2,
              "bbox": [
                199.0,
                1391.0,
                1494.0,
                1423.0
              ],
              "content": "trial, docket no. 180, is DENIED. Defendants' motion is premised on a misreading of the"
            },
            {
              "i": 3,
              "bbox": [
                196.0,
                1430.0,
                1460.0,
                1464.0
              ],
              "content": "United States Supreme Court's recent decision in Romag Fasteners, Inc. v. Fossil, Inc.,"
            },
            {
              "i": 4,
              "bbox": [
                201.0,
                1474.0,
                1363.0,
                1506.0
              ],
              "content": "140 S. Ct. 1492 (2020). Defendants contend that Romag rendered \"obsolete and"
            },
            {
              "i": 5,
              "bbox": [
                199.0,
                1515.0,
                1434.0,
                1547.0
              ],
              "content": "erroneous\" the legal standard pursuant to which the Court awarded to plaintiff certain"
            },
            {
              "i": 6,
              "bbox": [
                199.0,
                1556.0,
                1397.0,
                1588.0
              ],
              "content": "profits earned by defendants. The Court premised the disgorgement of profits on a"
            },
            {
              "i": 7,
              "bbox": [
                196.0,
                1597.0,
                1483.0,
                1629.0
              ],
              "content": "finding of willfulness. See Findings of Fact and Conclusions of Law at JI 32-60 (docket"
            },
            {
              "i": 8,
              "bbox": [
                199.0,
                1639.0,
                1467.0,
                1671.0
              ],
              "content": "no. 149). Contrary to defendants' assertion, the Romag Court did not cast any doubt on"
            },
            {
              "i": 9,
              "bbox": [
                199.0,
                1682.0,
                1390.0,
                1712.0
              ],
              "content": "the validity of an award of profits that is based on willful infringement. Rather, in"
            },
            {
              "i": 10,
              "bbox": [
                201.0,
                1723.0,
                1434.0,
                1755.0
              ],
              "content": "Romag, the Supreme Court held that, to recover a defendant's profits under 15 U.S.C"
            },
            {
              "i": 11,
              "bbox": [
                196.0,
                1762.0,
                1460.0,
                1792.0
              ],
              "content": "s 1117(a), a plaintiff need not necessarily prove willfulness. See 140 S. Ct. at 1495-97."
            },
            {
              "i": 12,
              "bbox": [
                196.0,
                1806.0,
                1467.0,
                1838.0
              ],
              "content": "In other words, in this case, plaintiff might have been entitled to the same disgorgement"
            },
            {
              "i": 13,
              "bbox": [
                199.0,
                1847.0,
                1418.0,
                1879.0
              ],
              "content": "of profits even if willful infringement had not been shown. Willfulness having been"
            },
            {
              "i": 14,
              "bbox": [
                196.0,
                1886.0,
                1432.0,
                1925.0
              ],
              "content": "established, however, the Court appropriately applied \"principles of equity\"' to award."
            },
            {
              "i": 15,
              "bbox": [
                194.0,
                1927.0,
                1402.0,
                1964.0
              ],
              "content": "certain profits attributable to the trademark infringement. See 15 U.S.C.  1117(a)."
            }
          ]
        },
        {
          "i": 12,
          "bbox": [
            197,
            2105,
            470,
            2139
          ],
          "type": "text",
          "lines": [
            {
              "i": 0,
              "bbox": [
                199.0,
                2108.0,
                471.0,
                2138.0
              ],
              "content": "MINUTE ORDER - 1"
            }
          ]
        }
      ]
    },
    {
      "i": 1,
      "blocks": [
        {
          "i": 0,
          "bbox": [
            317,
            38,
            1383,
            77
          ],
          "type": "abandon",
          "lines": [
            {
              "i": 0,
              "bbox": [
                322.3611195882161,
                43.57379807366265,
                1377.627902560764,
                76.90713140699599
              ],
              "content": "Case 2:17-cv-00894-TSZ   Document 187   Filed 06/05/20   Page 2 of 2"
            }
          ]
        },
        {
          "i": 1,
          "bbox": [
            125,
            127,
            188,
            2200
          ],
          "type": "abandon",
          "lines": [
            {
              "i": 0,
              "bbox": [
                152.000003390842,
                196.22664981418185,
                170.00000211927625,
                244.71865759955512
              ],
              "content": "1"
            },
            {
              "i": 1,
              "bbox": [
                152.000003390842,
                279.2266633775499,
                170.00000211927625,
                327.71867116292316
              ],
              "content": "2"
            },
            {
              "i": 2,
              "bbox": [
                152.000003390842,
                362.22669813368054,
                170.00000211927625,
                410.7186635335286
              ],
              "content": "3"
            },
            {
              "i": 3,
              "bbox": [
                152.000003390842,
                445.2267116970486,
                170.00000211927625,
                493.71867709689667
              ],
              "content": "4"
            },
            {
              "i": 4,
              "bbox": [
                152.000003390842,
                528.2267252604166,
                170.00000211927625,
                576.7186906602648
              ],
              "content": "5"
            },
            {
              "i": 5,
              "bbox": [
                152.000003390842,
                611.2267388237847,
                170.00000211927625,
                659.7187042236328
              ],
              "content": "6"
            },
            {
              "i": 6,
              "bbox": [
                152.000003390842,
                694.2267523871527,
                170.00000211927625,
                742.718760172526
              ],
              "content": "7"
            },
            {
              "i": 7,
              "bbox": [
                152.000003390842,
                777.5600009494358,
                170.00000211927625,
                826.052008734809
              ],
              "content": "8"
            },
            {
              "i": 8,
              "bbox": [
                152.000003390842,
                860.5600145128038,
                170.00000211927625,
                909.052022298177
              ],
              "content": "9"
            },
            {
              "i": 9,
              "bbox": [
                134.00000466240778,
                943.5600280761719,
                170.00000211927625,
                992.052035861545
              ],
              "content": "10"
            },
            {
              "i": 10,
              "bbox": [
                134.00000466240778,
                1026.5600416395398,
                170.00000211927625,
                1075.052049424913
              ],
              "content": "11"
            },
            {
              "i": 11,
              "bbox": [
                134.00000466240778,
                1109.560055202908,
                170.00000211927625,
                1158.0520629882812
              ],
              "content": "12"
            },
            {
              "i": 12,
              "bbox": [
                134.00000466240778,
                1192.5599839952256,
                170.00000211927625,
                1241.0519917805989
              ],
              "content": "13"
            },
            {
              "i": 13,
              "bbox": [
                134.00000466240778,
                1275.5599975585938,
                170.00000211927625,
                1324.052005343967
              ],
              "content": "14"
            },
            {
              "i": 14,
              "bbox": [
                134.00000466240778,
                1358.893330891927,
                170.00000211927625,
                1407.3853386773003
              ],
              "content": "15"
            },
            {
              "i": 15,
              "bbox": [
                134.00000466240778,
                1441.8933444552952,
                170.00000211927625,
                1490.385267469618
              ],
              "content": "16"
            },
            {
              "i": 16,
              "bbox": [
                134.00000466240778,
                1524.893358018663,
                170.00000211927625,
                1573.385281032986
              ],
              "content": "17"
            },
            {
              "i": 17,
              "bbox": [
                134.00000466240778,
                1607.8933715820312,
                170.00000211927625,
                1656.385294596354
              ],
              "content": "18"
            },
            {
              "i": 18,
              "bbox": [
                134.00000466240778,
                1690.8933851453992,
                170.00000211927625,
                1739.3853081597222
              ],
              "content": "19"
            },
            {
              "i": 19,
              "bbox": [
                134.00000466240778,
                1773.8933987087673,
                170.00000211927625,
                1822.38532172309
              ],
              "content": "20"
            },
            {
              "i": 20,
              "bbox": [
                134.00000466240778,
                1856.8934122721353,
                170.00000211927625,
                1905.3853352864583
              ],
              "content": "21"
            },
            {
              "i": 21,
              "bbox": [
                134.00000466240778,
                1940.2267456054688,
                170.00000211927625,
                1988.7186686197915
              ],
              "content": "22"
            },
            {
              "i": 22,
              "bbox": [
                134.00000466240778,
                2023.2267591688367,
                170.00000211927625,
                2071.7186821831597
              ],
              "content": "23"
            }
          ]
        },
        {
          "i": 2,
          "bbox": [
            198,
            199,
            1476,
            287
          ],
          "type": "text",
          "lines": [
            {
              "i": 0,
              "bbox": [
                300.0,
                196.55996958414713,
                350.97601148817273,
                245.0519773695204
              ],
              "content": "(2) "
            },
            {
              "i": 1,
              "bbox": [
                400.0080108642578,
                196.55996958414713,
                1477.199978298611,
                245.0519773695204
              ],
              "content": "The Clerk is directed to send a copy of this Minute Order to all counsel of "
            },
            {
              "i": 2,
              "bbox": [
                199.99201032850476,
                238.21188608805338,
                1226.8811543782551,
                286.70389387342664
              ],
              "content": "record and to the United States Court of Appeals for the Ninth Circuit. "
            }
          ]
        },
        {
          "i": 3,
          "bbox": [
            298,
            318,
            779,
            360
          ],
          "type": "text",
          "lines": [
            {
              "i": 0,
              "bbox": [
                300.0,
                312.5518586900499,
                786.3599989149305,
                361.0438452826606
              ],
              "content": "Dated this 4th day of June, 2020. "
            }
          ]
        },
        {
          "i": 4,
          "bbox": [
            893,
            432,
            1331,
            647
          ],
          "type": "text",
          "lines": [
            {
              "i": 0,
              "bbox": [
                900.0,
                429.2266845703125,
                1204.9919976128472,
                477.7186499701606
              ],
              "content": "William M. McCool "
            },
            {
              "i": 1,
              "bbox": [
                901.3333638509114,
                470.56003146701386,
                990.6493292914496,
                519.0519968668619
              ],
              "content": "Clerk "
            },
            {
              "i": 2,
              "bbox": [
                900.0,
                553.8933648003472,
                1112.6519944932725,
                602.3853302001953
              ],
              "content": "s/Karen Dews "
            },
            {
              "i": 3,
              "bbox": [
                901.3333638509114,
                595.2267116970486,
                1105.9933132595486,
                643.7186770968967
              ],
              "content": "Deputy Clerk "
            }
          ]
        },
        {
          "i": 5,
          "bbox": [
            197,
            2105,
            474,
            2139
          ],
          "type": "abandon",
          "lines": [
            {
              "i": 0,
              "bbox": [
                200.0,
                2101.4399210611978,
                478.33065456814234,
                2142.7480061848955
              ],
              "content": "MINUTE ORDER - 2 "
            }
          ]
        }
      ]
    }
  ]
}